stream_wars/__init__.py
stream_wars/frontend/build/asset-manifest.json
stream_wars/frontend/build/favicon.ico
stream_wars/frontend/build/index.html
stream_wars/frontend/build/logo192.png
stream_wars/frontend/build/logo512.png
stream_wars/frontend/build/manifest.json
stream_wars/frontend/build/precache-manifest.e169c48ee8a5b064e0ad02dd97cb7563.js
stream_wars/frontend/build/robots.txt
stream_wars/frontend/build/service-worker.js
stream_wars/frontend/build/static/css/main.e3314fdb.chunk.css
stream_wars/frontend/build/static/css/main.e3314fdb.chunk.css.map
stream_wars/frontend/build/static/js/2.29ebcd12.chunk.js
stream_wars/frontend/build/static/js/2.29ebcd12.chunk.js.LICENSE
stream_wars/frontend/build/static/js/2.29ebcd12.chunk.js.map
stream_wars/frontend/build/static/js/main.3e636c5f.chunk.js
stream_wars/frontend/build/static/js/main.3e636c5f.chunk.js.map
stream_wars/frontend/build/static/js/runtime-main.225e7569.js
stream_wars/frontend/build/static/js/runtime-main.225e7569.js.map
stream_wars/frontend/build/static/media/StarJediHollow.6d9a2d00.woff
stream_wars/frontend/build/static/media/StarJediHollow.f36aaf0d.woff2
stream_wars/frontend/build/static/media/volume_off.04238fc3.svg
stream_wars/frontend/build/static/media/volume_on.ef7f87ab.svg
stream_wars/py.typed
stream_wars-0.1.0.dist-info/LICENSE
stream_wars-0.1.0.dist-info/WHEEL
stream_wars-0.1.0.dist-info/METADATA
stream_wars-0.1.0.dist-info/RECORD
