Metadata-Version: 2.1
Name: stream-wars
Version: 0.1.0
Summary: Streamlit component to generate the Star Wars crawl text.
Home-page: https://murilo-cunha-stream-wars-stream-warsdocs-slmccu.streamlit.app/
License: MIT
Keywords: streamlit-components,streamlit,react
Author: Murilo Cunha
Author-email: murilo@dataroots.io
Requires-Python: >=3.8, !=2.7.*, !=3.0.*, !=3.1.*, !=3.2.*, !=3.3.*, !=3.4.*, !=3.5.*, !=3.6.*, !=3.7.*
Classifier: License :: OSI Approved :: MIT License
Classifier: Programming Language :: Python :: 3
Classifier: Programming Language :: Python :: 3.8
Classifier: Programming Language :: Python :: 3.9
Classifier: Programming Language :: Python :: 3.10
Classifier: Programming Language :: Python :: 3.11
Requires-Dist: streamlit (>=1.12.2,<2.0.0)
Project-URL: Repository, https://github.com/murilo-cunha/stream-wars
